Metadata-Version: 2.3
Name: ecoindex_scraper
Version: 3.15.0
Summary: Ecoindex_scraper module provides a way to scrape data from given website while simulating a real web browser
License: Creative Commons BY-NC-ND
Author: Vincent Vatelot
Author-email: vincent.vatelot@ik.me
Requires-Python: >=3.10,<4.0
Classifier: License :: Other/Proprietary License
Classifier: Programming Language :: Python :: 3
Classifier: Programming Language :: Python :: 3.10
Classifier: Programming Language :: Python :: 3.11
Classifier: Programming Language :: Python :: 3.12
Classifier: Programming Language :: Python :: 3.13
Requires-Dist: pillow (>=10.1.0,<11.0.0)
Requires-Dist: playwright (>=1.39.0,<2.0.0)
Requires-Dist: playwright-stealth (>=1.0.6,<2.0.0)
Requires-Dist: pydantic (>=2.4.2,<3.0.0)
Requires-Dist: pyyaml (>=6.0.1,<7.0.0)
Requires-Dist: setuptools (>=69.5.1,<71.0.0)
Requires-Dist: typing-extensions (>=4.8.0,<5.0.0)
Requires-Dist: ua-generator (>=2.0.5,<3.0.0)
Project-URL: Homepage, http://www.ecoindex.fr
Project-URL: Repository, https://github.com/cnumr/ecoindex_scrap_python
